movi/MOVI.py
movi/__init__.py
movi-0.5.2.dist-info/LICENSE
movi-0.5.2.dist-info/METADATA
movi-0.5.2.dist-info/WHEEL
movi-0.5.2.dist-info/top_level.txt
movi-0.5.2.dist-info/RECORD
