Metadata-Version: 2.1
Name: movi
Version: 0.5.2
Summary: Raspberry Pi API for MOVI Voice Dialog Shield.
Home-page: https://github.com/audeme/MOVIPiAPI
Author: Audeme
Author-email: fractor@audeme.com
License: Copyright (c) 2015--2018, Audeme, LLC
Requires-Dist: pyserial
